{"width":512,"imagePath":"dzmj_bg_tex.png","height":1024,"name":"dzmj_bg","SubTexture":[{"frameY":-4,"y":456,"frameWidth":50,"frameX":-5,"frameHeight":60,"width":40,"height":47,"name":"孔明灯3","x":246},{"frameY":-5,"y":443,"frameWidth":100,"frameX":-5,"frameHeight":100,"width":90,"height":90,"name":"fff053","x":410},{"frameY":-45,"y":443,"frameWidth":200,"frameX":-42,"frameHeight":200,"width":118,"height":111,"name":"Comp 3_05","x":290},{"frameY":-28,"y":161,"frameWidth":200,"frameX":-19,"frameHeight":200,"width":165,"height":157,"name":"Comp 3_13","x":179},{"frameY":-63,"y":535,"frameWidth":200,"frameX":-64,"frameHeight":200,"width":75,"height":72,"name":"Comp 3_00","x":410},{"frameY":-39,"y":454,"frameWidth":200,"frameX":-35,"frameHeight":200,"width":132,"height":126,"name":"Comp 3_07","x":1},{"frameY":-54,"y":582,"frameWidth":200,"frameX":-54,"frameHeight":200,"width":93,"height":89,"name":"Comp 3_02","x":1},{"frameY":-47,"y":456,"frameWidth":200,"frameX":-46,"frameHeight":200,"width":109,"height":106,"name":"Comp 3_04","x":135},{"frameY":-33,"y":312,"frameWidth":200,"frameX":-28,"frameHeight":200,"width":145,"height":140,"name":"Comp 3_09","x":1},{"frameY":-36,"y":320,"frameWidth":200,"frameX":-30,"frameHeight":200,"width":140,"height":134,"name":"Comp 3_08","x":148},{"frameY":-51,"y":564,"frameWidth":200,"frameX":-50,"frameHeight":200,"width":102,"height":97,"name":"Comp 3_03","x":135},{"frameY":-58,"y":322,"frameWidth":200,"frameX":-59,"frameHeight":200,"width":84,"height":80,"name":"Comp 3_01","x":417},{"frameY":-41,"y":322,"frameWidth":200,"frameX":-39,"frameHeight":200,"width":125,"height":119,"name":"Comp 3_06","x":290},{"frameY":-27,"y":1,"frameWidth":200,"frameX":-24,"frameHeight":200,"width":156,"height":155,"name":"Comp 3_11","x":350},{"frameY":-27,"y":1,"frameWidth":200,"frameX":-17,"frameHeight":200,"width":169,"height":158,"name":"Comp 3_14","x":179},{"frameY":-25,"y":1,"frameWidth":200,"frameX":-13,"frameHeight":200,"width":176,"height":160,"name":"Comp 3_15","x":1},{"frameY":-30,"y":163,"frameWidth":200,"frameX":-26,"frameHeight":200,"width":151,"height":147,"name":"Comp 3_10","x":1},{"frameY":-27,"y":161,"frameWidth":200,"frameX":-23,"frameHeight":200,"width":160,"height":159,"name":"Comp 3_12","x":346}]}