{"width":1024,"imagePath":"sdxl_yg_tex.png","height":2048,"name":"sdxl_yg","SubTexture":[{"width":319,"y":849,"height":442,"name":"后发","x":435},{"width":927,"y":1,"height":846,"name":"身体","x":1},{"width":83,"y":849,"height":203,"name":"右发","x":913},{"frameHeight":462,"y":1142,"frameX":0,"width":192,"frameY":0,"height":196,"name":"头","frameWidth":246,"x":756},{"width":432,"y":849,"height":395,"name":"刘海","x":1},{"width":155,"y":849,"height":291,"name":"左发","x":756},{"frameHeight":120,"y":1,"frameX":-7,"width":85,"frameY":-13,"height":94,"name":"杨过表情","frameWidth":100,"x":930}]}