{"frameRate":24,"name":"wild","version":"5.5","compatibleVersion":"5.5","armature":[{"type":"MovieClip","frameRate":24,"name":"fire_flow","bone":[{"name":"root"},{"name":"new (1)","parent":"root"}],"slot":[{"blendMode":"add","displayIndex":-1,"name":"new (1)","parent":"new (1)"}],"skin":[{"slot":[{"name":"new (1)","display":[{"name":"new (1)"},{"name":"new (2)"},{"name":"new (3)"},{"name":"new (4)"},{"name":"new (5)"},{"name":"new (6)"},{"name":"new (7)"},{"name":"new (8)"},{"name":"new (9)"},{"name":"new (10)"},{"name":"new (11)"},{"name":"new (12)"},{"name":"new (13)"},{"name":"new (14)"},{"name":"new (15)"},{"name":"new (16)"},{"name":"new (17)"},{"name":"new (18)"},{"name":"new (19)"},{"name":"new (20)"},{"name":"new (21)"},{"name":"new (22)"},{"name":"new (23)"},{"name":"new (24)"},{"name":"new (25)"},{"name":"new (26)"},{"name":"new (27)"},{"name":"new (28)"},{"name":"new (29)"},{"name":"new (30)"},{"name":"new (31)"}]}]}],"animation":[{"duration":61,"playTimes":0,"name":"fire_flow","slot":[{"name":"new (1)","displayFrame":[{"value":17},{},{"value":1},{"value":2},{"value":3},{"value":4},{"value":5},{"value":6},{"value":7},{"value":8},{"value":9},{"value":10},{"value":11},{"value":12},{"value":13},{"value":14},{"value":15},{"value":16},{"value":17},{},{"value":1},{"value":2},{"value":3},{"value":4},{"value":5},{"value":6},{"value":7},{"value":8},{"value":9},{"value":10},{"value":11},{"value":12},{"value":13},{"value":14},{"value":15},{"value":16},{"value":17},{},{"value":1},{"value":2},{"value":3},{"value":4},{"value":5},{"value":6},{"value":7},{"value":8},{"value":9},{"value":10},{"value":11},{"value":12},{"value":13},{"value":14},{"value":15},{"value":16},{"value":17},{"value":18},{"value":19},{"value":20},{"value":21},{"value":22},{"value":23},{"duration":0,"value":-1}]}]}],"defaultActions":[{"gotoAndPlay":"fire_flow"}]}]}