{"width":1024,"imagePath":"cbzz_icon_3_tex.png","height":2048,"name":"cbzz_icon_3","SubTexture":[{"frameHeight":196,"y":1,"frameX":-14,"width":175,"frameY":-16,"height":163,"name":"特效图标1_0003s_0002_3","frameWidth":206,"x":364},{"frameHeight":196,"y":1,"frameX":-14,"width":175,"frameY":-16,"height":163,"name":"特效图标1_0003s_0001_2","frameWidth":206,"x":187},{"frameHeight":196,"y":164,"frameX":-15,"width":175,"frameY":-15,"height":161,"name":"Comp 7_09","frameWidth":206,"x":541},{"frameHeight":196,"y":502,"frameX":-15,"width":175,"frameY":-15,"height":161,"name":"Comp 7_29","frameWidth":206,"x":1},{"frameHeight":196,"y":665,"frameX":-15,"width":175,"frameY":-15,"height":161,"name":"Comp 7_08","frameWidth":206,"x":1},{"frameHeight":196,"y":329,"frameX":-15,"width":175,"frameY":-15,"height":161,"name":"Comp 7_05","frameWidth":206,"x":355},{"frameHeight":196,"y":828,"frameX":-15,"width":175,"frameY":-15,"height":161,"name":"Comp 7_27","frameWidth":206,"x":1},{"frameHeight":196,"y":816,"frameX":-15,"width":175,"frameY":-15,"height":161,"name":"Comp 7_25","frameWidth":206,"x":532},{"frameHeight":196,"y":981,"frameX":-15,"width":175,"frameY":-15,"height":158,"name":"Comp 7_07","frameWidth":206,"x":178},{"frameHeight":196,"y":492,"frameX":-15,"width":175,"frameY":-15,"height":161,"name":"Comp 7_26","frameWidth":206,"x":718},{"frameHeight":196,"y":327,"frameX":-15,"width":175,"frameY":-15,"height":161,"name":"Comp 7_06","frameWidth":206,"x":541},{"frameHeight":196,"y":166,"frameX":-15,"width":175,"frameY":-15,"height":161,"name":"Comp 7_23","frameWidth":206,"x":187},{"frameHeight":196,"y":981,"frameX":-15,"width":175,"frameY":-15,"height":161,"name":"Comp 7_04","frameWidth":206,"x":709},{"frameHeight":196,"y":655,"frameX":-15,"width":175,"frameY":-15,"height":161,"name":"Comp 7_24","frameWidth":206,"x":355},{"frameHeight":196,"y":1,"frameX":-15,"width":175,"frameY":-15,"height":161,"name":"Comp 7_03","frameWidth":206,"x":541},{"frameHeight":196,"y":339,"frameX":-15,"width":175,"frameY":-15,"height":161,"name":"Comp 7_22","frameWidth":206,"x":1},{"frameHeight":196,"y":653,"frameX":-15,"width":175,"frameY":-15,"height":161,"name":"Comp 7_02","frameWidth":206,"x":532},{"frameHeight":196,"y":166,"frameX":-15,"width":175,"frameY":-15,"height":161,"name":"Comp 7_21","frameWidth":206,"x":364},{"frameHeight":196,"y":329,"frameX":-15,"width":175,"frameY":-15,"height":161,"name":"Comp 7_01","frameWidth":206,"x":178},{"frameHeight":196,"y":492,"frameX":-15,"width":175,"frameY":-15,"height":161,"name":"Comp 7_18","frameWidth":206,"x":355},{"frameHeight":196,"y":194,"frameX":-188,"width":2,"frameY":-160,"height":8,"name":"Comp 7_00","frameWidth":206,"x":182},{"frameHeight":196,"y":1,"frameX":-15,"width":175,"frameY":-15,"height":161,"name":"Comp 7_20","frameWidth":206,"x":718},{"frameHeight":196,"y":818,"frameX":-15,"width":175,"frameY":-15,"height":161,"name":"Comp 7_17","frameWidth":206,"x":709},{"frameHeight":196,"y":329,"frameX":-15,"width":175,"frameY":-15,"height":161,"name":"Comp 7_19","frameWidth":206,"x":718},{"frameHeight":196,"y":176,"frameX":-16,"width":1,"frameY":-158,"height":5,"name":"Comp 7_35","frameWidth":206,"x":184},{"frameHeight":196,"y":991,"frameX":-15,"width":175,"frameY":-24,"height":152,"name":"Comp 7_16","frameWidth":206,"x":1},{"frameHeight":196,"y":655,"frameX":-15,"width":175,"frameY":-15,"height":161,"name":"Comp 7_15","frameWidth":206,"x":178},{"frameHeight":196,"y":194,"frameX":-16,"width":2,"frameY":-158,"height":8,"name":"Comp 7_34","frameWidth":206,"x":178},{"frameHeight":196,"y":164,"frameX":-15,"width":175,"frameY":-15,"height":161,"name":"Comp 7_14","frameWidth":206,"x":718},{"frameHeight":196,"y":981,"frameX":-15,"width":71,"frameY":-15,"height":157,"name":"Comp 7_32","frameWidth":206,"x":355},{"frameHeight":196,"y":818,"frameX":-15,"width":175,"frameY":-15,"height":161,"name":"Comp 7_12","frameWidth":206,"x":355},{"frameHeight":196,"y":176,"frameX":-15,"width":4,"frameY":-154,"height":16,"name":"Comp 7_33","frameWidth":206,"x":178},{"frameHeight":196,"y":655,"frameX":-15,"width":175,"frameY":-15,"height":161,"name":"Comp 7_13","frameWidth":206,"x":709},{"frameHeight":196,"y":979,"frameX":-15,"width":175,"frameY":-15,"height":161,"name":"Comp 7_31","frameWidth":206,"x":532},{"frameHeight":196,"y":176,"frameX":-15,"width":175,"frameY":-15,"height":161,"name":"Comp 7_11","frameWidth":206,"x":1},{"frameHeight":196,"y":490,"frameX":-15,"width":175,"frameY":-15,"height":161,"name":"Comp 7_30","frameWidth":206,"x":532},{"frameHeight":196,"y":492,"frameX":-15,"width":175,"frameY":-15,"height":161,"name":"Comp 7_10","frameWidth":206,"x":178},{"frameHeight":196,"y":818,"frameX":-15,"width":175,"frameY":-15,"height":161,"name":"Comp 7_28","frameWidth":206,"x":178},{"frameHeight":196,"y":1,"frameX":-10,"width":184,"frameY":-12,"height":173,"name":"特效图标1_0003s_0000_1","frameWidth":206,"x":1}]}